grove_watcher/__init__.py
grove_watcher/__main__.py
grove_watcher/_version.py
grove_watcher/models.py
grove_watcher/ts_lang_fetcher.py
grove_watcher/venv_manager.py
grove_watcher/config/__init__.py
grove_watcher/config/config.py
grove_watcher/config/logger_loader.py
grove_watcher-1.0.0.dist-info/AUTHORS.rst
grove_watcher-1.0.0.dist-info/LICENSE.txt
grove_watcher-1.0.0.dist-info/METADATA
grove_watcher-1.0.0.dist-info/WHEEL
grove_watcher-1.0.0.dist-info/entry_points.txt
grove_watcher-1.0.0.dist-info/top_level.txt
grove_watcher-1.0.0.dist-info/RECORD
