Metadata-Version: 2.2
Name: grove-watcher
Version: 1.0.0
Summary: Tree Sitter grammar fetcher for Python
Author-email: ukw2d <ukw2d@outlook.com>
License: MIT
Project-URL: homepage, https://github.com/ukw2d/py-grove-watcher
Project-URL: repository, https://github.com/ukw2d/py-grove-watcher
Project-URL: documentation, https://github.com/ukw2d/py-grove-watcher
Requires-Python: >=3.9
License-File: LICENSE.txt
License-File: AUTHORS.rst
Requires-Dist: importlib-metadata
Requires-Dist: tree-sitter<0.24.0
Requires-Dist: pydantic
Requires-Dist: pydantic_settings
